LICENSE
jarniadice/__init__.py
jarniadice/__main__.py
jarniadice/expr.py
jarniadice-0.1.3.dist-info/LICENSE
jarniadice-0.1.3.dist-info/WHEEL
jarniadice-0.1.3.dist-info/METADATA
jarniadice-0.1.3.dist-info/RECORD
